LICENSE
MANIFEST.in
README.rst
setup.py
pymd5/__init__.py
pymd5.egg-info/PKG-INFO
pymd5.egg-info/SOURCES.txt
pymd5.egg-info/dependency_links.txt
pymd5.egg-info/entry_points.txt
pymd5.egg-info/top_level.txt