Metadata-Version: 1.1
Name: pymd5
Version: 0.1
Summary: Recursively calculate and display MD5 file hashes for all files rooted in a directory.
Home-page: https://github.com/richmilne/pymd5/releases/tag/v0.1
Author: Richard Milne
Author-email: richmilne@hotmail.com
License: MIT
Platform: UNKNOWN
Classifier: Development Status :: 4 - Beta
Classifier: Environment :: Console
Classifier: License :: OSI Approved :: MIT License
Classifier: Operating System :: POSIX
Classifier: Programming Language :: Python :: 2
Classifier: Programming Language :: Python :: 3
